altdata/__init__.py
altdata-0.0.1.dist-info/METADATA
altdata-0.0.1.dist-info/WHEEL
altdata-0.0.1.dist-info/top_level.txt
altdata-0.0.1.dist-info/RECORD
