Metadata-Version: 2.4
Name: altdata
Version: 0.0.1
Summary: Alt data package.
Author-email: Your Name <jdry1729@gmail.com>
